vocompr/__init__.py
vocompr/utils.py
vocompr/vocompr.py
vocompr-0.1.3.dist-info/LICENSE
vocompr-0.1.3.dist-info/METADATA
vocompr-0.1.3.dist-info/WHEEL
vocompr-0.1.3.dist-info/top_level.txt
vocompr-0.1.3.dist-info/RECORD
