Metadata-Version: 2.1
Name: vocompr
Version: 0.1.3
Summary: Python implementation of vocompr text compression algorithm
Home-page: http://github.com/EnzoBnl/vocompr
Author: Enzo Bonnal
Author-email: enzobonnal@gmail.com
License: Apache 2.
Platform: UNKNOWN
